setup.py
dsnd_probability0331/Binomialdistribution.py
dsnd_probability0331/Gaussiandistribution.py
dsnd_probability0331/Generaldistribution.py
dsnd_probability0331/__init__.py
dsnd_probability0331.egg-info/PKG-INFO
dsnd_probability0331.egg-info/SOURCES.txt
dsnd_probability0331.egg-info/dependency_links.txt
dsnd_probability0331.egg-info/not-zip-safe
dsnd_probability0331.egg-info/top_level.txt