Metadata-Version: 1.0
Name: dsnd-probability0331
Version: 0.1
Summary: Gaussian and Binomial distributions
Home-page: UNKNOWN
Author: Josh Lu
Author-email: myemail@something.com
License: UNKNOWN
Platform: UNKNOWN
